calculus_of_variations/__init__.py
calculus_of_variations/abstract_problem.py
calculus_of_variations/boltz_problem.py
calculus_of_variations/higher_derivatives_problem.py
calculus_of_variations/isoperimetric_problem.py
calculus_of_variations/multidimensional_problem.py
calculus_of_variations/simplest_problem.py
calculus_of_variations/utils.py
calculus_of_variations-0.3.0.dist-info/LICENSE
calculus_of_variations-0.3.0.dist-info/METADATA
calculus_of_variations-0.3.0.dist-info/WHEEL
calculus_of_variations-0.3.0.dist-info/top_level.txt
calculus_of_variations-0.3.0.dist-info/RECORD
