Metadata-Version: 2.1
Name: calculus-of-variations
Version: 0.3.0
Summary: Project on solving the Calculus of variations problems using symbolic mathematics
Home-page: https://github.com/dayyass/calculus-of-variations
Author: Dani El-Ayyass
Author-email: dayyass@yandex.ru
License: UNKNOWN
Project-URL: Bug Tracker, https://github.com/dayyass/calculus-of-variations/issues
Platform: UNKNOWN
Classifier: Programming Language :: Python :: 3
Classifier: License :: OSI Approved :: MIT License
Classifier: Operating System :: OS Independent
Requires-Python: >=3.6
License-File: LICENSE
Requires-Dist: sympy (==1.6.2)
